htmltable2csv/__init__.py
htmltable2csv/htmltable2csv.py
htmltable2csv/parser.py
htmltable2csv-0.6.0.dist-info/LICENSE
htmltable2csv-0.6.0.dist-info/METADATA
htmltable2csv-0.6.0.dist-info/WHEEL
htmltable2csv-0.6.0.dist-info/top_level.txt
htmltable2csv-0.6.0.dist-info/RECORD
