Metadata-Version: 2.1
Name: htmltable2csv
Version: 0.6.0
Summary: Transform HTML tables in a Web Page to CSV files.
Home-page: https://github.com/aqib-git/htmltable2csv
Author: Aqib
Author-email: aqib@codecrud.com
License: UNKNOWN
Platform: UNKNOWN
Classifier: Programming Language :: Python :: 3
Classifier: License :: OSI Approved :: MIT License
Classifier: Operating System :: OS Independent
Requires-Python: >=3.6
